{"packages/cupertino_icons/assets/CupertinoIcons.ttf":["packages/cupertino_icons/assets/CupertinoIcons.ttf"],"res/ceo.jpg":["res/ceo.jpg"],"res/fund.png":["res/fund.png"],"res/logo.png":["res/logo.png"],"res/logo.svg":["res/logo.svg"],"res/map.png":["res/map.png"],"res/mercedes.png":["res/mercedes.png"],"res/phone.png":["res/phone.png"],"res/present.png":["res/present.png"],"res/profile.png":["res/profile.png"],"res/profile.svg":["res/profile.svg"],"res/rectangle.png":["res/rectangle.png"],"res/teddy.png":["res/teddy.png"],"res/wheel.png":["res/wheel.png"]}